fastapi_initializr/__init__.py
fastapi_initializr/main.py
fastapi_initializr-1.0.3.dist-info/METADATA
fastapi_initializr-1.0.3.dist-info/WHEEL
fastapi_initializr-1.0.3.dist-info/entry_points.txt
fastapi_initializr-1.0.3.dist-info/top_level.txt
fastapi_initializr-1.0.3.dist-info/RECORD
