Metadata-Version: 2.4
Name: fastapi-initializr
Version: 1.0.3
Summary: A modern CLI tool that instantly scaffolds production-ready FastAPI project structures with best practices, interactive prompts, and optional configurations.
Author-email: Saad Sabahuddin <saadmdsabahuddin@gmail.com>
License: MIT
Project-URL: Repository, https://github.com/saadmdsabah/fastapi-initializr.git
Project-URL: Issues, https://github.com/saadmdsabah/fastapi-initializr/issues
Project-URL: DOWNLOAD, https://github.com/saadmdsabah/fastapi-initializr/archive/refs/heads/main.zip
Keywords: fastapi,initializr,cli,project-generator,scaffold,template,web-development,python-cli,api,boilerplate,framework,starter-project
Requires-Python: >=3.8
Requires-Dist: questionary
Requires-Dist: colorama
Requires-Dist: requests
Requires-Dist: yaspin
Dynamic: requires-python
